mjjo/__init__.py
mjjo/bjd.py
mjjo/bjdconnector.py
mjjo/convaddr.py
mjjo/cordate.py
mjjo/data/__init__.py
mjjo/data/bjd.txt
mjjo/data/bjd_changed.txt
mjjo/data/bjd_connectors.pkl
mjjo/data/bjd_current.txt
mjjo/data/bjd_frequency_dictionary.txt
mjjo/data/bjd_smallest.txt
mjjo/data/date_dictionary.txt
mjjo/data/full_bjd_connectors.pkl
mjjo/data/multiple_word_sgg_list.txt
mjjo/library/__init__.py
mjjo/library/data.py
tests/__init__.py
tests/test_convaddr.py
tests/test_cordate.py
tests/tests.py
vos_mjjo-1.0.5.dist-info/LICENSE
vos_mjjo-1.0.5.dist-info/METADATA
vos_mjjo-1.0.5.dist-info/WHEEL
vos_mjjo-1.0.5.dist-info/entry_points.txt
vos_mjjo-1.0.5.dist-info/top_level.txt
vos_mjjo-1.0.5.dist-info/RECORD
