Metadata-Version: 2.1
Name: vos-mjjo
Version: 1.0.5
Summary: This library is designed to correct dates in building permit records
Home-page: https://github.com/jomujin/vos-mjjo
Author: mjjo
Author-email: mj.jo@valueofspace.com
Classifier: Programming Language :: Python :: 3
Classifier: License :: OSI Approved :: MIT License
Classifier: Operating System :: OS Independent
Requires-Python: >=3.7
License-File: LICENSE
Requires-Dist: symspellpy
Requires-Dist: pandas
